libman/__init__.py
libman/config.py
libman/exceptions.py
libman/extractors.py
libman/image_util.py
libman/story.py
libman/types.py
libman/utils.py
libman/zones.py
libman/mixins/__init__.py
libman/mixins/account.py
libman/mixins/album.py
libman/mixins/auth.py
libman/mixins/bloks.py
libman/mixins/challenge.py
libman/mixins/clip.py
libman/mixins/collection.py
libman/mixins/comment.py
libman/mixins/direct.py
libman/mixins/explore.py
libman/mixins/fbsearch.py
libman/mixins/fundraiser.py
libman/mixins/hashtag.py
libman/mixins/highlight.py
libman/mixins/igtv.py
libman/mixins/insights.py
libman/mixins/location.py
libman/mixins/media.py
libman/mixins/multiple_accounts.py
libman/mixins/note.py
libman/mixins/notification.py
libman/mixins/password.py
libman/mixins/photo.py
libman/mixins/private.py
libman/mixins/public.py
libman/mixins/share.py
libman/mixins/signup.py
libman/mixins/story.py
libman/mixins/timeline.py
libman/mixins/totp.py
libman/mixins/track.py
libman/mixins/user.py
libman/mixins/video.py
libman-2.1.3.dist-info/LICENSE
libman-2.1.3.dist-info/METADATA
libman-2.1.3.dist-info/WHEEL
libman-2.1.3.dist-info/top_level.txt
libman-2.1.3.dist-info/RECORD
