Metadata-Version: 2.1
Name: libman
Version: 2.1.3
Summary: Fast and effective Instagram Private API wrapper
Home-page: https://github.com/libman/libman
Author: Libman
Author-email: libman@libman.ai
License: MIT
Keywords: instagram private api,instagram-private-api,instagram api,instagram-api,instagram,instagram-scraper,instagram-client,instagram-stories,instagram-feed,instagram-reels,instagram-insights,downloader,uploader,videos,photos,albums,igtv,reels,stories,pictures,instagram-user-photos,instagram-photos,instagram-metadata,instagram-downloader,instagram-uploader,instagram-note
Classifier: Development Status :: 4 - Beta
Classifier: Intended Audience :: Developers
Classifier: License :: OSI Approved :: MIT License
Classifier: Topic :: Software Development :: Libraries :: Python Modules
Classifier: Programming Language :: Python :: 3.9
Classifier: Programming Language :: Python :: 3.10
Requires-Python: >=3.9
License-File: LICENSE
Requires-Dist: requests<3.0,>=2.25.1
Requires-Dist: PySocks==1.7.1
Requires-Dist: pydantic==2.9.2
Requires-Dist: pycryptodomex==3.21.0
